{
    "boxShadow": "none",
    "widgetName": "lastname_input",
    "iconSVG": "/static/media/icon.9f505595.svg",
    "displayName": "Input",
    "topRow": 5.2,
    "bottomRow": 11.8,
    "parentRowSpace": 10,
    "autoFocus": false,
    "type": "INPUT_WIDGET_V2",
    "hideCard": false,
    "animateLoading": false,
    "parentColumnSpace": 10.5390625,
    "dynamicTriggerPathList": [],
    "resetOnSubmit": true,
    "leftColumn": 0,
    "dynamicBindingPathList": [{"key": "accentColor"}],
    "labelPosition": "Top",
    "labelStyle": "",
    "labelTextColor": "#2e3d49",
    "inputType": "TEXT",
    "maxChars": "20",
    "isDisabled": false,
    "validation": "true",
    "flexVerticalAlignment": "end",
    "key": "0equv9lg65",
    "labelTextSize": "0.875rem",
    "isRequired": true,
    "rightColumn": 32,
    "dynamicHeight": "FIXED",
    "accentColor": "{{appsmith.theme.colors.primaryColor}}",
    "widgetId": "17016catca",
    "minWidth": 450,
    "isVisible": "true",
    "label": "姓/ Last name",
    "version": 2,
    "parentId": "f6o5ujc94b",
    "isLoading": false,
    "renderMode": "CANVAS",
    "regex": "",
    "originalTopRow": 13,
    "responsiveBehavior": "fill",
    "borderRadius": "0px",
    "maxDynamicHeight": 9000,
    "originalBottomRow": 17,
    "iconAlign": "left",
    "defaultText": "",
    "alignment": "center",
    "minDynamicHeight": 4
}